setup.py
rnc_mlnd_distributions/Binomialdistribution.py
rnc_mlnd_distributions/Gaussiandistribution.py
rnc_mlnd_distributions/Generaldistribution.py
rnc_mlnd_distributions/__init__.py
rnc_mlnd_distributions.egg-info/PKG-INFO
rnc_mlnd_distributions.egg-info/SOURCES.txt
rnc_mlnd_distributions.egg-info/dependency_links.txt
rnc_mlnd_distributions.egg-info/not-zip-safe
rnc_mlnd_distributions.egg-info/top_level.txt