Metadata-Version: 1.0
Name: rnc-mlnd-distributions
Version: 0.1
Summary: Gaussian & Binomial probability distributions
Home-page: UNKNOWN
Author: Raghu Nandan Chilukuri
Author-email: raghu.rnc@gmail.com
License: UNKNOWN
Platform: UNKNOWN
